qim3d/__init__.py
qim3d/cli/__init__.py
qim3d/css/annotation_tool.css
qim3d/css/gradio.css
qim3d/detection/__init__.py
qim3d/detection/_common_detection_methods.py
qim3d/examples/NT_128x128x128.tif
qim3d/examples/__init__.py
qim3d/examples/bone_128x128x128.tif
qim3d/examples/cement_128x128x128.tif
qim3d/examples/fibers_150x150x150.tif
qim3d/examples/fly_150x256x256.tif
qim3d/examples/shell_225x128x128.tif
qim3d/examples/slice_218x193.png
qim3d/examples/__pycache__/__init__.cpython-311.pyc
qim3d/features/__init__.py
qim3d/features/_common_features_methods.py
qim3d/filters/__init__.py
qim3d/filters/_common_filter_methods.py
qim3d/generate/__init__.py
qim3d/generate/_aggregators.py
qim3d/generate/_generators.py
qim3d/gui/__init__.py
qim3d/gui/annotation_tool.py
qim3d/gui/data_explorer.py
qim3d/gui/interface.py
qim3d/gui/iso3d.py
qim3d/gui/layers2d.py
qim3d/gui/local_thickness.py
qim3d/gui/qim_theme.py
qim3d/gui/volume_generator.py
qim3d/io/__init__.py
qim3d/io/_convert.py
qim3d/io/_downloader.py
qim3d/io/_loading.py
qim3d/io/_ome_zarr.py
qim3d/io/_saving.py
qim3d/io/_sync.py
qim3d/io/_txrm.py
qim3d/mesh/__init__.py
qim3d/mesh/_common_mesh_methods.py
qim3d/ml/__init__.py
qim3d/ml/_augmentations.py
qim3d/ml/_data.py
qim3d/ml/_ml_utils.py
qim3d/ml/models/__init__.py
qim3d/ml/models/_unet.py
qim3d/morphology/__init__.py
qim3d/morphology/_common_morphologies.py
qim3d/operations/__init__.py
qim3d/operations/_common_operations_methods.py
qim3d/operations/_slicing_operations.py
qim3d/operations/_volume_operations.py
qim3d/processing/__init__.py
qim3d/processing/_layers.py
qim3d/processing/_local_thickness.py
qim3d/processing/_structure_tensor.py
qim3d/segmentation/__init__.py
qim3d/segmentation/_common_segmentation_methods.py
qim3d/segmentation/_connected_components.py
qim3d/tests/__init__.py
qim3d/utils/__init__.py
qim3d/utils/_cli.py
qim3d/utils/_decorators.py
qim3d/utils/_dependencies.py
qim3d/utils/_doi.py
qim3d/utils/_logger.py
qim3d/utils/_misc.py
qim3d-1.4.0.dist-info/METADATA
qim3d-1.4.0.dist-info/WHEEL
qim3d-1.4.0.dist-info/entry_points.txt
qim3d-1.4.0.dist-info/top_level.txt
qim3d-1.4.0.dist-info/RECORD
