Metadata-Version: 2.4
Name: qim3d
Version: 1.4.0
Summary: QIM tools and user interfaces for volumetric imaging
Author-email: Felipe Delestro <fima@dtu.dk>
License-Expression: MIT
Project-URL: Homepage, https://platform.qim.dk/qim3d
Classifier: Programming Language :: Python :: 3
Classifier: Development Status :: 5 - Production/Stable
Classifier: Intended Audience :: Education
Classifier: Intended Audience :: Science/Research
Classifier: Natural Language :: English
Classifier: Operating System :: OS Independent
Classifier: Topic :: Scientific/Engineering :: Image Processing
Classifier: Topic :: Scientific/Engineering :: Visualization
Classifier: Topic :: Software Development :: User Interfaces
Requires-Python: >=3.11
Requires-Dist: h5py>=3.9.0
Requires-Dist: localthickness>=0.1.2
Requires-Dist: matplotlib>=3.8.0
Requires-Dist: pydicom==2.4.4
Requires-Dist: numpy>=1.26.0
Requires-Dist: outputformat>=0.1.3
Requires-Dist: Pillow>=10.0.1
Requires-Dist: plotly>=5.14.1
Requires-Dist: scipy>=1.11.2
Requires-Dist: seaborn>=0.12.2
Requires-Dist: tifffile>=2025.1.10
Requires-Dist: imagecodecs>=2024.12.30
Requires-Dist: tqdm>=4.65.0
Requires-Dist: nibabel>=5.2.0
Requires-Dist: ipywidgets>=8.1.2
Requires-Dist: dask>=2023.6.0
Requires-Dist: k3d>=2.17
Requires-Dist: olefile>=0.46
Requires-Dist: psutil>=5.9.0
Requires-Dist: structure-tensor>=0.2.1
Requires-Dist: zarr>=3.0
Requires-Dist: ome_zarr>=0.12.0
Requires-Dist: dask-image>=2024.5.3
Requires-Dist: scikit-image>=0.24.0
Requires-Dist: trimesh>=4.4.9
Requires-Dist: PyGEL3D>=0.6.1
Requires-Dist: slgbuilder>=0.2.1
Requires-Dist: pyvista[jupyter]>=0.45
Requires-Dist: imageio-ffmpeg>=0.6
Requires-Dist: numcodecs<0.16
Requires-Dist: pygorpho>=1.0.1
Provides-Extra: deep-learning
Requires-Dist: torch>=2.0.1; extra == "deep-learning"
Requires-Dist: torchvision>=0.15.2; extra == "deep-learning"
Requires-Dist: torchinfo>=1.8.0; extra == "deep-learning"
Requires-Dist: monai>=1.2.0; extra == "deep-learning"
Provides-Extra: synthetic-data
Requires-Dist: noise>=1.2.2; extra == "synthetic-data"
Provides-Extra: gui
Requires-Dist: gradio>=5.1; extra == "gui"
Requires-Dist: fastapi>=0.109.0; extra == "gui"
Requires-Dist: uvicorn[standard]>=0.27.0; extra == "gui"
Provides-Extra: all
Requires-Dist: gradio>=5.1; extra == "all"
Requires-Dist: fastapi>=0.109.0; extra == "all"
Requires-Dist: uvicorn[standard]>=0.27.0; extra == "all"
Requires-Dist: torch>=2.0.1; extra == "all"
Requires-Dist: torchvision>=0.15.2; extra == "all"
Requires-Dist: torchinfo>=1.8.0; extra == "all"
Requires-Dist: monai>=1.2.0; extra == "all"
Requires-Dist: noise>=1.2.2; extra == "all"
